siglent/__init__.py
siglent/analysis.py
siglent/automation.py
siglent/channel.py
siglent/exceptions.py
siglent/math_channel.py
siglent/measurement.py
siglent/measurement_config.py
siglent/models.py
siglent/oscilloscope.py
siglent/power_supply.py
siglent/power_supply_output.py
siglent/protocol_decode.py
siglent/psu_data_logger.py
siglent/psu_models.py
siglent/psu_scpi_commands.py
siglent/py.typed
siglent/reference_waveform.py
siglent/scpi_commands.py
siglent/screen_capture.py
siglent/trigger.py
siglent/vector_graphics.py
siglent/waveform.py
siglent/connection/__init__.py
siglent/connection/base.py
siglent/connection/mock.py
siglent/connection/socket.py
siglent/connection/visa_connection.py
siglent/gui/__init__.py
siglent/gui/app.py
siglent/gui/connection_manager.py
siglent/gui/live_view_worker.py
siglent/gui/main_window.py
siglent/gui/vnc_window.py
siglent/gui/waveform_capture_worker.py
siglent/gui/utils/validators.py
siglent/gui/widgets/__init__.py
siglent/gui/widgets/channel_control.py
siglent/gui/widgets/cursor_panel.py
siglent/gui/widgets/error_dialog.py
siglent/gui/widgets/fft_display.py
siglent/gui/widgets/math_panel.py
siglent/gui/widgets/measurement_marker.py
siglent/gui/widgets/measurement_panel.py
siglent/gui/widgets/protocol_decode_panel.py
siglent/gui/widgets/psu_control.py
siglent/gui/widgets/reference_panel.py
siglent/gui/widgets/scope_web_view.py
siglent/gui/widgets/terminal_widget.py
siglent/gui/widgets/timebase_control.py
siglent/gui/widgets/trigger_control.py
siglent/gui/widgets/vector_graphics_panel.py
siglent/gui/widgets/visual_measurement_panel.py
siglent/gui/widgets/waveform_display.py
siglent/gui/widgets/waveform_display_pg.py
siglent/gui/widgets/measurement_markers/__init__.py
siglent/gui/widgets/measurement_markers/frequency_marker.py
siglent/gui/widgets/measurement_markers/timing_marker.py
siglent/gui/widgets/measurement_markers/voltage_marker.py
siglent/protocol_decoders/__init__.py
siglent/protocol_decoders/i2c_decoder.py
siglent_oscilloscope-0.5.1.dist-info/licenses/LICENSE
siglent_oscilloscope-0.5.1.dist-info/METADATA
siglent_oscilloscope-0.5.1.dist-info/WHEEL
siglent_oscilloscope-0.5.1.dist-info/entry_points.txt
siglent_oscilloscope-0.5.1.dist-info/top_level.txt
siglent_oscilloscope-0.5.1.dist-info/RECORD
