Metadata-Version: 2.4
Name: Siglent-Oscilloscope
Version: 0.5.1
Summary: Python library for Siglent oscilloscope and power supply control via SCPI over Ethernet/LAN. Oscilloscope support: SDS800XHD, SDS1000X-E, SDS2000X Plus, SDS5000X with waveform capture, measurements, FFT analysis, and PyQt6 GUI. Power supply support: SPD3303X series with programmatic control, data logging, and automation. Automated test report generation with AI analysis.
Author: Robin Mumm
Maintainer: little-did-I-know
License: MIT
Project-URL: Homepage, https://github.com/little-did-I-know/Siglent-Oscilloscope
Project-URL: Documentation, https://little-did-I-know.github.io/Siglent-Oscilloscope/
Project-URL: Repository, https://github.com/little-did-I-know/Siglent-Oscilloscope
Project-URL: Issues, https://github.com/little-did-I-know/Siglent-Oscilloscope/issues
Project-URL: Changelog, https://github.com/little-did-I-know/Siglent-Oscilloscope/blob/main/CHANGELOG.md
Keywords: siglent,oscilloscope,power supply,SDS,SPD,SCPI,test equipment,instrumentation,measurement,waveform,automation,data acquisition,lab automation,PyQt6,GUI,FFT,protocol decoder,I2C,SPI,UART,real-time,visualization,PSU,voltage,current
Classifier: Development Status :: 4 - Beta
Classifier: Intended Audience :: Science/Research
Classifier: Intended Audience :: Developers
Classifier: Operating System :: OS Independent
Classifier: Programming Language :: Python :: 3
Classifier: Programming Language :: Python :: 3.8
Classifier: Programming Language :: Python :: 3.9
Classifier: Programming Language :: Python :: 3.10
Classifier: Programming Language :: Python :: 3.11
Classifier: Programming Language :: Python :: 3.12
Classifier: Programming Language :: Python :: 3 :: Only
Classifier: Topic :: Scientific/Engineering
Classifier: Topic :: Scientific/Engineering :: Interface Engine/Protocol Translator
Classifier: Topic :: System :: Hardware :: Hardware Drivers
Classifier: Topic :: System :: Networking :: Monitoring
Classifier: Topic :: Software Development :: Libraries :: Python Modules
Classifier: Environment :: X11 Applications :: Qt
Classifier: Typing :: Typed
Requires-Python: >=3.8
License-File: LICENSE
Requires-Dist: numpy>=1.24.0
Requires-Dist: matplotlib>=3.7.0
Requires-Dist: scipy>=1.10.0
Provides-Extra: dev
Requires-Dist: pytest>=7.0; extra == "dev"
Requires-Dist: pytest-cov>=4.0.0; extra == "dev"
Requires-Dist: codecov>=2.1.0; extra == "dev"
Requires-Dist: black>=23.0; extra == "dev"
Requires-Dist: flake8>=6.0; extra == "dev"
Requires-Dist: build>=0.10.0; extra == "dev"
Requires-Dist: twine>=4.0.0; extra == "dev"
Requires-Dist: black[jupyter]>=23.0; extra == "dev"
Provides-Extra: hdf5
Requires-Dist: h5py>=3.8.0; extra == "hdf5"
Provides-Extra: gui
Requires-Dist: PyQt6>=6.6.0; extra == "gui"
Requires-Dist: PyQt6-WebEngine>=6.6.0; extra == "gui"
Requires-Dist: pyqtgraph>=0.13.0; extra == "gui"
Provides-Extra: fun
Requires-Dist: shapely>=2.0.0; extra == "fun"
Requires-Dist: Pillow>=10.0.0; extra == "fun"
Requires-Dist: svgpathtools>=1.6.0; extra == "fun"
Provides-Extra: report-generator
Requires-Dist: PyQt6>=6.6.0; extra == "report-generator"
Requires-Dist: Pillow>=10.0.0; extra == "report-generator"
Requires-Dist: requests>=2.31.0; extra == "report-generator"
Requires-Dist: reportlab>=4.0.0; extra == "report-generator"
Requires-Dist: ollama>=0.6.0; extra == "report-generator"
Provides-Extra: power-supply-beta
Provides-Extra: usb
Requires-Dist: pyvisa>=1.14.0; extra == "usb"
Requires-Dist: pyvisa-py>=0.7.0; extra == "usb"
Provides-Extra: experimental
Provides-Extra: docs
Requires-Dist: mkdocs>=1.5.0; extra == "docs"
Requires-Dist: mkdocs-material>=9.5.0; extra == "docs"
Requires-Dist: mkdocstrings[python]>=0.24.0; extra == "docs"
Requires-Dist: mkdocs-gen-files>=0.5.0; extra == "docs"
Requires-Dist: mkdocs-literate-nav>=0.6.0; extra == "docs"
Requires-Dist: mkdocs-section-index>=0.3.0; extra == "docs"
Provides-Extra: build-exe
Requires-Dist: pyinstaller>=6.0.0; extra == "build-exe"
Provides-Extra: all
Requires-Dist: h5py>=3.8.0; extra == "all"
Requires-Dist: PyQt6>=6.6.0; extra == "all"
Requires-Dist: PyQt6-WebEngine>=6.6.0; extra == "all"
Requires-Dist: pyqtgraph>=0.13.0; extra == "all"
Requires-Dist: shapely>=2.0.0; extra == "all"
Requires-Dist: Pillow>=10.0.0; extra == "all"
Requires-Dist: svgpathtools>=1.6.0; extra == "all"
Requires-Dist: requests>=2.31.0; extra == "all"
Requires-Dist: reportlab>=4.0.0; extra == "all"
Requires-Dist: ollama>=0.6.0; extra == "all"
Dynamic: license-file
